discordplus/__init__.py
discordplus/coglib.py
discordplus/errors.py
discordplus/extra.py
discordplus/lib.py
discordplus/task.py
discordplus/classes/__init__.py
discordplus/classes/classes.py
discordplus/classes/configs.py
discordplus/classes/models.py
discordplus/database/__init__.py
discordplus/database/database.py
discordplus/database/translation.py
discordplus/emotes/__emotes.py
discordplus/emotes/__init__.py
discordplus/emotes/activities.yml
discordplus/emotes/flags.yml
discordplus/emotes/food.yml
discordplus/emotes/nature.yml
discordplus/emotes/objects.yml
discordplus/emotes/people.yml
discordplus/emotes/symbols.yml
discordplus/emotes/travel.yml
discordplus/models/__init__.py
discordplus/models/dynamic.py
discordplus/models/ineractions.py
discordplus-1.4.1.dist-info/LICENSE
discordplus-1.4.1.dist-info/METADATA
discordplus-1.4.1.dist-info/WHEEL
discordplus-1.4.1.dist-info/top_level.txt
discordplus-1.4.1.dist-info/RECORD
