Metadata-Version: 2.1
Name: discordplus
Version: 1.4.1
Summary: Extra tools for discord.py developers
Home-page: https://github.com/ashenguard/discord-plus
Author: Ashenguard
Author-email: Ashenguard@agmdev.com
License: MIT License
Platform: UNKNOWN
Classifier: Programming Language :: Python :: 3
Classifier: License :: OSI Approved :: MIT License
Classifier: Development Status :: 4 - Beta
Classifier: Operating System :: OS Independent
Requires-Python: >=3.8
Requires-Dist: pyyaml
Requires-Dist: flask
Requires-Dist: requests
Requires-Dist: discord-py-interactions
Requires-Dist: discord.py
